[{"Задач поставлено":1.0,"Data-debatЫ":0.0,"Фед округ":"ЦФО","Место в рейтинге":7.0,"Data-хакатоны":24.0,"Ретинг по развитию сообщества":4.61,"Рейтинг по внедрению":21.0,"Место по внедрениям":3.0,"Общий рейтинг":26.53,"Рейтинг регионов по задачам":0.93,"Разместил цифровую практику на СМАРТЕКЕ":1.0,"Цифровой наставник":2.0,"Количество команд победителей из региона":1.0,"Субъект РФ":"Белгородская область","Задач отобрано":1.0,"Задач внедрено":2.0,"Место по сообществам":13.0,"Место по задачам":24.0,"Задач решено":1.0},{"Задач поставлено":1.0,"Data-debatЫ":0.0,"Фед округ":"ЦФО","Место в рейтинге":63.0,"Data-хакатоны":9.0,"Ретинг по развитию сообщества":0.0,"Рейтинг по внедрению":0.0,"Место по внедрениям":0.0,"Общий рейтинг":0.3,"Рейтинг регионов по задачам":0.3,"Разместил цифровую практику на СМАРТЕКЕ":0.0,"Цифровой наставник":0.0,"Количество команд победителей из региона":0.0,"Субъект РФ":"Брянская область","Задач отобрано":1.0,"Задач внедрено":0.0,"Место по сообществам":0.0,"Место по задачам":27.0,"Задач решено":0.0},{"Задач поставлено":1.0,"Data-debatЫ":0.0,"Фед округ":"ЦФО","Место в рейтинге":30.0,"Data-хакатоны":13.0,"Ретинг по развитию сообщества":0.0,"Рейтинг по внедрению":8.0,"Место по внедрениям":12.0,"Общий рейтинг":8.05,"Рейтинг регионов по задачам":0.05,"Разместил цифровую практику на СМАРТЕКЕ":0.0,"Цифровой наставник":0.0,"Количество команд победителей из региона":0.0,"Субъект РФ":"Владимирская область","Задач отобрано":0.0,"Задач внедрено":2.0,"Место по сообществам":0.0,"Место по задачам":31.0,"Задач решено":0.0},{"Задач поставлено":1.0,"Data-debatЫ":0.0,"Фед округ":"ЦФО","Место в рейтинге":39.0,"Data-хакатоны":21.0,"Ретинг по развитию сообщества":0.0,"Рейтинг по внедрению":6.0,"Место по внедрениям":13.0,"Общий рейтинг":6.15,"Рейтинг регионов по задачам":0.15,"Разместил цифровую практику на СМАРТЕКЕ":0.0,"Цифровой наставник":0.0,"Количество команд победителей из региона":0.0,"Субъект РФ":"Воронежская область","Задач отобрано":0.0,"Задач внедрено":1.0,"Место по сообществам":0.0,"Место по задачам":30.0,"Задач решено":0.0},{"Задач поставлено":0.0,"Data-debatЫ":0.0,"Фед округ":"ЦФО","Место в рейтинге":0.0,"Data-хакатоны":11.0,"Ретинг по развитию сообщества":0.0,"Рейтинг по внедрению":0.0,"Место по внедрениям":0.0,"Общий рейтинг":0.0,"Рейтинг регионов по задачам":0.0,"Разместил цифровую практику на СМАРТЕКЕ":0.0,"Цифровой наставник":0.0,"Количество команд победителей из региона":0.0,"Субъект РФ":"Ивановская область","Задач отобрано":0.0,"Задач внедрено":0.0,"Место по сообществам":0.0,"Место по задачам":0.0,"Задач решено":0.0},{"Задач поставлено":1.0,"Data-debatЫ":0.0,"Фед округ":"ЦФО","Место в рейтинге":59.0,"Data-хакатоны":29.0,"Ретинг по развитию сообщества":0.79,"Рейтинг по внедрению":0.0,"Место по внедрениям":0.0,"Общий рейтинг":0.94,"Рейтинг регионов по задачам":0.15,"Разместил цифровую практику на СМАРТЕКЕ":0.0,"Цифровой наставник":0.0,"Количество команд победителей из региона":0.0,"Субъект РФ":"Калужская область","Задач отобрано":0.0,"Задач внедрено":0.0,"Место по сообществам":37.0,"Место по задачам":30.0,"Задач решено":0.0},{"Задач поставлено":1.0,"Data-debatЫ":0.0,"Фед округ":"ЦФО","Место в рейтинге":51.0,"Data-хакатоны":24.0,"Ретинг по развитию сообщества":0.79,"Рейтинг по внедрению":2.0,"Место по внедрениям":14.0,"Общий рейтинг":2.84,"Рейтинг регионов по задачам":0.05,"Разместил цифровую практику на СМАРТЕКЕ":0.0,"Цифровой наставник":0.0,"Количество команд победителей из региона":0.0,"Субъект РФ":"Костромская область","Задач отобрано":0.0,"Задач внедрено":1.0,"Место по сообществам":36.0,"Место по задачам":31.0,"Задач решено":0.0},{"Задач поставлено":1.0,"Data-debatЫ":0.0,"Фед округ":"ЦФО","Место в рейтинге":20.0,"Data-хакатоны":56.0,"Ретинг по развитию сообщества":0.89,"Рейтинг по внедрению":8.0,"Место по внедрениям":12.0,"Общий рейтинг":11.66,"Рейтинг регионов по задачам":2.78,"Разместил цифровую практику на СМАРТЕКЕ":0.0,"Цифровой наставник":0.0,"Количество команд победителей из региона":0.0,"Субъект РФ":"Курская область","Задач отобрано":1.0,"Задач внедрено":2.0,"Место по сообществам":30.0,"Место по задачам":15.0,"Задач решено":2.5},{"Задач поставлено":2.0,"Data-debatЫ":1.0,"Фед округ":"ЦФО","Место в рейтинге":9.0,"Data-хакатоны":97.0,"Ретинг по развитию сообщества":4.49,"Рейтинг по внедрению":20.0,"Место по внедрениям":4.0,"Общий рейтинг":25.69,"Рейтинг регионов по задачам":1.2,"Разместил цифровую практику на СМАРТЕКЕ":2.0,"Цифровой наставник":2.0,"Количество команд победителей из региона":0.0,"Субъект РФ":"Липецкая область","Задач отобрано":2.0,"Задач внедрено":2.0,"Место по сообществам":14.0,"Место по задачам":20.0,"Задач решено":0.0},{"Задач поставлено":19.0,"Data-debatЫ":2.0,"Фед округ":"ЦФО","Место в рейтинге":1.0,"Data-хакатоны":771.0,"Ретинг по развитию сообщества":110.62,"Рейтинг по внедрению":19.0,"Место по внедрениям":5.0,"Общий рейтинг":144.45,"Рейтинг регионов по задачам":14.83,"Разместил цифровую практику на СМАРТЕКЕ":1.0,"Цифровой наставник":0.0,"Количество команд победителей из региона":7.0,"Субъект РФ":"Москва","Задач отобрано":9.0,"Задач внедрено":2.0,"Место по сообществам":1.0,"Место по задачам":2.0,"Задач решено":7.5},{"Задач поставлено":2.0,"Data-debatЫ":0.0,"Фед округ":"ЦФО","Место в рейтинге":19.0,"Data-хакатоны":68.0,"Ретинг по развитию сообщества":3.9,"Рейтинг по внедрению":8.0,"Место по внедрениям":12.0,"Общий рейтинг":12.1,"Рейтинг регионов по задачам":0.2,"Разместил цифровую практику на СМАРТЕКЕ":0.0,"Цифровой наставник":0.0,"Количество команд победителей из региона":1.0,"Субъект РФ":"Московская область","Задач отобрано":0.0,"Задач внедрено":2.0,"Место по сообществам":15.0,"Место по задачам":29.0,"Задач решено":0.0},{"Задач поставлено":0.0,"Data-debatЫ":0.0,"Фед округ":"ЦФО","Место в рейтинге":0.0,"Data-хакатоны":13.0,"Ретинг по развитию сообщества":0.0,"Рейтинг по внедрению":0.0,"Место по внедрениям":0.0,"Общий рейтинг":0.0,"Рейтинг регионов по задачам":0.0,"Разместил цифровую практику на СМАРТЕКЕ":0.0,"Цифровой наставник":0.0,"Количество команд победителей из региона":0.0,"Субъект РФ":"Орловская область","Задач отобрано":0.0,"Задач внедрено":0.0,"Место по сообществам":0.0,"Место по задачам":0.0,"Задач решено":0.0},{"Задач поставлено":4.0,"Data-debatЫ":0.0,"Фед округ":"ЦФО","Место в рейтинге":16.0,"Data-хакатоны":32.0,"Ретинг по развитию сообщества":2.38,"Рейтинг по внедрению":11.0,"Место по внедрениям":10.0,"Общий рейтинг":14.75,"Рейтинг регионов по задачам":1.38,"Разместил цифровую практику на СМАРТЕКЕ":1.0,"Цифровой наставник":0.0,"Количество команд победителей из региона":1.0,"Субъект РФ":"Рязанская область","Задач отобрано":1.0,"Задач внедрено":2.0,"Место по сообществам":23.0,"Место по задачам":17.0,"Задач решено":1.0},{"Задач поставлено":0.0,"Data-debatЫ":0.0,"Фед округ":"ЦФО","Место в рейтинге":41.0,"Data-хакатоны":8.0,"Ретинг по развитию сообщества":0.0,"Рейтинг по внедрению":6.0,"Место по внедрениям":13.0,"Общий рейтинг":6.0,"Рейтинг регионов по задачам":0.0,"Разместил цифровую практику на СМАРТЕКЕ":0.0,"Цифровой наставник":0.0,"Количество команд победителей из региона":0.0,"Субъект РФ":"Смоленская область","Задач отобрано":0.0,"Задач внедрено":1.0,"Место по сообществам":0.0,"Место по задачам":0.0,"Задач решено":0.0},{"Задач поставлено":0.0,"Data-debatЫ":0.0,"Фед округ":"ЦФО","Место в рейтинге":0.0,"Data-хакатоны":24.0,"Ретинг по развитию сообщества":0.0,"Рейтинг по внедрению":0.0,"Место по внедрениям":0.0,"Общий рейтинг":0.0,"Рейтинг регионов по задачам":0.0,"Разместил цифровую практику на СМАРТЕКЕ":0.0,"Цифровой наставник":0.0,"Количество команд победителей из региона":0.0,"Субъект РФ":"Тамбовская область","Задач отобрано":0.0,"Задач внедрено":0.0,"Место по сообществам":0.0,"Место по задачам":0.0,"Задач решено":0.0},{"Задач поставлено":3.0,"Data-debatЫ":0.0,"Фед округ":"ЦФО","Место в рейтинге":54.0,"Data-хакатоны":27.0,"Ретинг по развитию сообщества":0.78,"Рейтинг по внедрению":0.0,"Место по внедрениям":0.0,"Общий рейтинг":1.98,"Рейтинг регионов по задачам":1.2,"Разместил цифровую практику на СМАРТЕКЕ":0.0,"Цифровой наставник":0.0,"Количество команд победителей из региона":0.0,"Субъект РФ":"Тверская область","Задач отобрано":1.0,"Задач внедрено":0.0,"Место по сообществам":39.0,"Место по задачам":20.0,"Задач решено":0.0},{"Задач поставлено":2.0,"Data-debatЫ":0.0,"Фед округ":"ЦФО","Место в рейтинге":47.0,"Data-хакатоны":40.0,"Ретинг по развитию сообщества":0.8,"Рейтинг по внедрению":0.0,"Место по внедрениям":0.0,"Общий рейтинг":3.62,"Рейтинг регионов по задачам":2.83,"Разместил цифровую практику на СМАРТЕКЕ":0.0,"Цифровой наставник":0.0,"Количество команд победителей из региона":0.0,"Субъект РФ":"Тульская область","Задач отобрано":1.0,"Задач внедрено":0.0,"Место по сообществам":34.0,"Место по задачам":13.0,"Задач решено":2.5},{"Задач поставлено":1.0,"Data-debatЫ":1.0,"Фед округ":"ЦФО","Место в рейтинге":48.0,"Data-хакатоны":73.0,"Ретинг по развитию сообщества":3.47,"Рейтинг по внедрению":0.0,"Место по внедрениям":0.0,"Общий рейтинг":3.52,"Рейтинг регионов по задачам":0.05,"Разместил цифровую практику на СМАРТЕКЕ":0.0,"Цифровой наставник":0.0,"Количество команд победителей из региона":0.0,"Субъект РФ":"Ярославская область","Задач отобрано":0.0,"Задач внедрено":0.0,"Место по сообществам":17.0,"Место по задачам":31.0,"Задач решено":0.0},{"Задач поставлено":0.0,"Data-debatЫ":0.0,"Фед округ":"ПФО","Место в рейтинге":0.0,"Data-хакатоны":21.0,"Ретинг по развитию сообщества":0.0,"Рейтинг по внедрению":0.0,"Место по внедрениям":0.0,"Общий рейтинг":0.0,"Рейтинг регионов по задачам":0.0,"Разместил цифровую практику на СМАРТЕКЕ":0.0,"Цифровой наставник":0.0,"Количество команд победителей из региона":0.0,"Субъект РФ":"Кировская область","Задач отобрано":0.0,"Задач внедрено":0.0,"Место по сообществам":0.0,"Место по задачам":0.0,"Задач решено":0.0},{"Задач поставлено":1.0,"Data-debatЫ":0.0,"Фед округ":"ПФО","Место в рейтинге":40.0,"Data-хакатоны":33.0,"Ретинг по развитию сообщества":0.0,"Рейтинг по внедрению":6.0,"Место по внедрениям":13.0,"Общий рейтинг":6.05,"Рейтинг регионов по задачам":0.05,"Разместил цифровую практику на СМАРТЕКЕ":0.0,"Цифровой наставник":0.0,"Количество команд победителей из региона":0.0,"Субъект РФ":"Нижегородская область","Задач отобрано":0.0,"Задач внедрено":1.0,"Место по сообществам":0.0,"Место по задачам":31.0,"Задач решено":0.0},{"Задач поставлено":0.0,"Data-debatЫ":0.0,"Фед округ":"ПФО","Место в рейтинге":41.0,"Data-хакатоны":15.0,"Ретинг по развитию сообщества":0.0,"Рейтинг по внедрению":6.0,"Место по внедрениям":13.0,"Общий рейтинг":6.0,"Рейтинг регионов по задачам":0.0,"Разместил цифровую практику на СМАРТЕКЕ":0.0,"Цифровой наставник":0.0,"Количество команд победителей из региона":0.0,"Субъект РФ":"Оренбургская область","Задач отобрано":0.0,"Задач внедрено":1.0,"Место по сообществам":0.0,"Место по задачам":0.0,"Задач решено":0.0},{"Задач поставлено":1.0,"Data-debatЫ":0.0,"Фед округ":"ПФО","Место в рейтинге":57.0,"Data-хакатоны":62.0,"Ретинг по развитию сообщества":0.89,"Рейтинг по внедрению":0.0,"Место по внедрениям":0.0,"Общий рейтинг":1.19,"Рейтинг регионов по задачам":0.3,"Разместил цифровую практику на СМАРТЕКЕ":0.0,"Цифровой наставник":0.0,"Количество команд победителей из региона":0.0,"Субъект РФ":"Пензенская область","Задач отобрано":1.0,"Задач внедрено":0.0,"Место по сообществам":30.0,"Место по задачам":27.0,"Задач решено":0.0},{"Задач поставлено":1.0,"Data-debatЫ":0.0,"Фед округ":"ПФО","Место в рейтинге":13.0,"Data-хакатоны":36.0,"Ретинг по развитию сообщества":0.0,"Рейтинг по внедрению":21.0,"Место по внедрениям":3.0,"Общий рейтинг":21.3,"Рейтинг регионов по задачам":0.3,"Разместил цифровую практику на СМАРТЕКЕ":3.0,"Цифровой наставник":1.0,"Количество команд победителей из региона":0.0,"Субъект РФ":"Пермский край","Задач отобрано":1.0,"Задач внедрено":3.0,"Место по сообществам":0.0,"Место по задачам":27.0,"Задач решено":0.0},{"Задач поставлено":3.0,"Data-debatЫ":0.0,"Фед округ":"ПФО","Место в рейтинге":36.0,"Data-хакатоны":67.0,"Ретинг по развитию сообщества":0.81,"Рейтинг по внедрению":6.0,"Место по внедрениям":13.0,"Общий рейтинг":7.06,"Рейтинг регионов по задачам":0.25,"Разместил цифровую практику на СМАРТЕКЕ":0.0,"Цифровой наставник":0.0,"Количество команд победителей из региона":0.0,"Субъект РФ":"Республика Башкортостан","Задач отобрано":0.0,"Задач внедрено":1.0,"Место по сообществам":33.0,"Место по задачам":28.0,"Задач решено":0.0},{"Задач поставлено":0.0,"Data-debatЫ":0.0,"Фед округ":"ПФО","Место в рейтинге":0.0,"Data-хакатоны":22.0,"Ретинг по развитию сообщества":0.0,"Рейтинг по внедрению":0.0,"Место по внедрениям":0.0,"Общий рейтинг":0.0,"Рейтинг регионов по задачам":0.0,"Разместил цифровую практику на СМАРТЕКЕ":0.0,"Цифровой наставник":0.0,"Количество команд победителей из региона":0.0,"Субъект РФ":"Республика Марий Эл","Задач отобрано":0.0,"Задач внедрено":0.0,"Место по сообществам":0.0,"Место по задачам":0.0,"Задач решено":0.0},{"Задач поставлено":1.0,"Data-debatЫ":0.0,"Фед округ":"ПФО","Место в рейтинге":44.0,"Data-хакатоны":37.0,"Ретинг по развитию сообщества":4.94,"Рейтинг по внедрению":0.0,"Место по внедрениям":0.0,"Общий рейтинг":5.09,"Рейтинг регионов по задачам":0.15,"Разместил цифровую практику на СМАРТЕКЕ":0.0,"Цифровой наставник":0.0,"Количество команд победителей из региона":1.0,"Субъект РФ":"Республика Мордовия","Задач отобрано":0.0,"Задач внедрено":0.0,"Место по сообществам":11.0,"Место по задачам":30.0,"Задач решено":0.0},{"Задач поставлено":12.0,"Data-debatЫ":0.0,"Фед округ":"ПФО","Место в рейтинге":11.0,"Data-хакатоны":68.0,"Ретинг по развитию сообщества":2.41,"Рейтинг по внедрению":12.0,"Место по внедрениям":9.0,"Общий рейтинг":23.01,"Рейтинг регионов по задачам":8.6,"Разместил цифровую практику на СМАРТЕКЕ":0.0,"Цифровой наставник":0.0,"Количество команд победителей из региона":1.0,"Субъект РФ":"Республика Татарстан (Татарстан)","Задач отобрано":5.0,"Задач внедрено":2.0,"Место по сообществам":22.0,"Место по задачам":4.0,"Задач решено":5.0},{"Задач поставлено":0.0,"Data-debatЫ":0.0,"Фед округ":"ПФО","Место в рейтинге":37.0,"Data-хакатоны":88.0,"Ретинг по развитию сообщества":0.86,"Рейтинг по внедрению":6.0,"Место по внедрениям":13.0,"Общий рейтинг":6.86,"Рейтинг регионов по задачам":0.0,"Разместил цифровую практику на СМАРТЕКЕ":0.0,"Цифровой наставник":0.0,"Количество команд победителей из региона":0.0,"Субъект РФ":"Самарская область","Задач отобрано":0.0,"Задач внедрено":1.0,"Место по сообществам":31.0,"Место по задачам":0.0,"Задач решено":0.0},{"Задач поставлено":4.0,"Data-debatЫ":0.0,"Фед округ":"ПФО","Место в рейтинге":34.0,"Data-хакатоны":155.0,"Ретинг по развитию сообщества":1.22,"Рейтинг по внедрению":6.0,"Место по внедрениям":13.0,"Общий рейтинг":7.42,"Рейтинг регионов по задачам":0.2,"Разместил цифровую практику на СМАРТЕКЕ":0.0,"Цифровой наставник":0.0,"Количество команд победителей из региона":0.0,"Субъект РФ":"Саратовская область","Задач отобрано":0.0,"Задач внедрено":1.0,"Место по сообществам":27.0,"Место по задачам":29.0,"Задач решено":0.0},{"Задач поставлено":0.0,"Data-debatЫ":0.0,"Фед округ":"ПФО","Место в рейтинге":41.0,"Data-хакатоны":14.0,"Ретинг по развитию сообщества":0.0,"Рейтинг по внедрению":6.0,"Место по внедрениям":13.0,"Общий рейтинг":6.0,"Рейтинг регионов по задачам":0.0,"Разместил цифровую практику на СМАРТЕКЕ":0.0,"Цифровой наставник":0.0,"Количество команд победителей из региона":0.0,"Субъект РФ":"Удмуртская Республика","Задач отобрано":0.0,"Задач внедрено":1.0,"Место по сообществам":0.0,"Место по задачам":0.0,"Задач решено":0.0},{"Задач поставлено":8.0,"Data-debatЫ":1.0,"Фед округ":"ПФО","Место в рейтинге":12.0,"Data-хакатоны":74.0,"Ретинг по развитию сообщества":5.35,"Рейтинг по внедрению":12.0,"Место по внедрениям":9.0,"Общий рейтинг":21.82,"Рейтинг регионов по задачам":4.48,"Разместил цифровую практику на СМАРТЕКЕ":0.0,"Цифровой наставник":0.0,"Количество команд победителей из региона":1.0,"Субъект РФ":"Ульяновская область","Задач отобрано":2.0,"Задач внедрено":2.0,"Место по сообществам":9.0,"Место по задачам":10.0,"Задач решено":2.5},{"Задач поставлено":0.0,"Data-debatЫ":0.0,"Фед округ":"ПФО","Место в рейтинге":0.0,"Data-хакатоны":16.0,"Ретинг по развитию сообщества":0.0,"Рейтинг по внедрению":0.0,"Место по внедрениям":0.0,"Общий рейтинг":0.0,"Рейтинг регионов по задачам":0.0,"Разместил цифровую практику на СМАРТЕКЕ":0.0,"Цифровой наставник":0.0,"Количество команд победителей из региона":0.0,"Субъект РФ":"Чувашская Республика- Чувашия","Задач отобрано":0.0,"Задач внедрено":0.0,"Место по сообществам":0.0,"Место по задачам":0.0,"Задач решено":0.0},{"Задач поставлено":2.0,"Data-debatЫ":0.0,"Фед округ":"СКФО","Место в рейтинге":43.0,"Data-хакатоны":19.0,"Ретинг по развитию сообщества":4.63,"Рейтинг по внедрению":0.0,"Место по внедрениям":0.0,"Общий рейтинг":5.68,"Рейтинг регионов по задачам":1.05,"Разместил цифровую практику на СМАРТЕКЕ":0.0,"Цифровой наставник":0.0,"Количество команд победителей из региона":1.0,"Субъект РФ":"Кабардино-Балкарская Республика","Задач отобрано":1.0,"Задач внедрено":0.0,"Место по сообществам":12.0,"Место по задачам":22.0,"Задач решено":0.0},{"Задач поставлено":1.0,"Data-debatЫ":0.0,"Фед округ":"СКФО","Место в рейтинге":65.0,"Data-хакатоны":0.0,"Ретинг по развитию сообщества":0.0,"Рейтинг по внедрению":0.0,"Место по внедрениям":0.0,"Общий рейтинг":0.05,"Рейтинг регионов по задачам":0.05,"Разместил цифровую практику на СМАРТЕКЕ":0.0,"Цифровой наставник":0.0,"Количество команд победителей из региона":0.0,"Субъект РФ":"Карачаево-Черкесская Республика","Задач отобрано":0.0,"Задач внедрено":0.0,"Место по сообществам":0.0,"Место по задачам":31.0,"Задач решено":0.0},{"Задач поставлено":1.0,"Data-debatЫ":0.0,"Фед округ":"СКФО","Место в рейтинге":39.0,"Data-хакатоны":11.0,"Ретинг по развитию сообщества":0.0,"Рейтинг по внедрению":6.0,"Место по внедрениям":13.0,"Общий рейтинг":6.15,"Рейтинг регионов по задачам":0.15,"Разместил цифровую практику на СМАРТЕКЕ":0.0,"Цифровой наставник":0.0,"Количество команд победителей из региона":0.0,"Субъект РФ":"Республика Дагестан","Задач отобрано":0.0,"Задач внедрено":1.0,"Место по сообществам":0.0,"Место по задачам":30.0,"Задач решено":0.0},{"Задач поставлено":0.0,"Data-debatЫ":0.0,"Фед округ":"СКФО","Место в рейтинге":0.0,"Data-хакатоны":2.0,"Ретинг по развитию сообщества":0.0,"Рейтинг по внедрению":0.0,"Место по внедрениям":0.0,"Общий рейтинг":0.0,"Рейтинг регионов по задачам":0.0,"Разместил цифровую практику на СМАРТЕКЕ":0.0,"Цифровой наставник":0.0,"Количество команд победителей из региона":0.0,"Субъект РФ":"Республика Ингушетия","Задач отобрано":0.0,"Задач внедрено":0.0,"Место по сообществам":0.0,"Место по задачам":0.0,"Задач решено":0.0},{"Задач поставлено":1.0,"Data-debatЫ":0.0,"Фед округ":"СКФО","Место в рейтинге":63.0,"Data-хакатоны":4.0,"Ретинг по развитию сообщества":0.0,"Рейтинг по внедрению":0.0,"Место по внедрениям":0.0,"Общий рейтинг":0.3,"Рейтинг регионов по задачам":0.3,"Разместил цифровую практику на СМАРТЕКЕ":0.0,"Цифровой наставник":0.0,"Количество команд победителей из региона":0.0,"Субъект РФ":"Республика Северная Осетия-Алания","Задач отобрано":1.0,"Задач внедрено":0.0,"Место по сообществам":0.0,"Место по задачам":27.0,"Задач решено":0.0},{"Задач поставлено":2.0,"Data-debatЫ":0.0,"Фед округ":"СКФО","Место в рейтинге":31.0,"Data-хакатоны":45.0,"Ретинг по развитию сообщества":0.79,"Рейтинг по внедрению":6.0,"Место по внедрениям":13.0,"Общий рейтинг":7.74,"Рейтинг регионов по задачам":0.95,"Разместил цифровую практику на СМАРТЕКЕ":0.0,"Цифровой наставник":0.0,"Количество команд победителей из региона":0.0,"Субъект РФ":"Ставропольский край","Задач отобрано":1.0,"Задач внедрено":1.0,"Место по сообществам":38.0,"Место по задачам":23.0,"Задач решено":0.0},{"Задач поставлено":2.0,"Data-debatЫ":0.0,"Фед округ":"СКФО","Место в рейтинге":33.0,"Data-хакатоны":69.0,"Ретинг по развитию сообщества":1.24,"Рейтинг по внедрению":6.0,"Место по внедрениям":13.0,"Общий рейтинг":7.54,"Рейтинг регионов по задачам":0.3,"Разместил цифровую практику на СМАРТЕКЕ":0.0,"Цифровой наставник":0.0,"Количество команд победителей из региона":0.0,"Субъект РФ":"Чеченская Республика","Задач отобрано":0.0,"Задач внедрено":1.0,"Место по сообществам":26.0,"Место по задачам":27.0,"Задач решено":0.0},{"Задач поставлено":2.0,"Data-debatЫ":1.0,"Фед округ":"ЮФО","Место в рейтинге":45.0,"Data-хакатоны":37.0,"Ретинг по развитию сообщества":2.98,"Рейтинг по внедрению":0.0,"Место по внедрениям":0.0,"Общий рейтинг":4.06,"Рейтинг регионов по задачам":1.08,"Разместил цифровую практику на СМАРТЕКЕ":0.0,"Цифровой наставник":0.0,"Количество команд победителей из региона":0.0,"Субъект РФ":"Астраханская область","Задач отобрано":1.0,"Задач внедрено":0.0,"Место по сообществам":19.0,"Место по задачам":21.0,"Задач решено":1.0},{"Задач поставлено":0.0,"Data-debatЫ":0.0,"Фед округ":"ЮФО","Место в рейтинге":32.0,"Data-хакатоны":105.0,"Ретинг по развитию сообщества":7.59,"Рейтинг по внедрению":0.0,"Место по внедрениям":0.0,"Общий рейтинг":7.59,"Рейтинг регионов по задачам":0.0,"Разместил цифровую практику на СМАРТЕКЕ":0.0,"Цифровой наставник":0.0,"Количество команд победителей из региона":2.0,"Субъект РФ":"Волгоградская область","Задач отобрано":0.0,"Задач внедрено":0.0,"Место по сообществам":6.0,"Место по задачам":0.0,"Задач решено":0.0},{"Задач поставлено":0.0,"Data-debatЫ":0.0,"Фед округ":"ЮФО","Место в рейтинге":38.0,"Data-хакатоны":20.0,"Ретинг по развитию сообщества":0.79,"Рейтинг по внедрению":6.0,"Место по внедрениям":13.0,"Общий рейтинг":6.79,"Рейтинг регионов по задачам":0.0,"Разместил цифровую практику на СМАРТЕКЕ":0.0,"Цифровой наставник":0.0,"Количество команд победителей из региона":0.0,"Субъект РФ":"Севастополь","Задач отобрано":0.0,"Задач внедрено":1.0,"Место по сообществам":35.0,"Место по задачам":0.0,"Задач решено":0.0},{"Задач поставлено":2.0,"Data-debatЫ":0.0,"Фед округ":"ЮФО","Место в рейтинге":23.0,"Data-хакатоны":40.0,"Ретинг по развитию сообщества":0.77,"Рейтинг по внедрению":6.0,"Место по внедрениям":13.0,"Общий рейтинг":9.59,"Рейтинг регионов по задачам":2.83,"Разместил цифровую практику на СМАРТЕКЕ":0.0,"Цифровой наставник":0.0,"Количество команд победителей из региона":0.0,"Субъект РФ":"Краснодарский край","Задач отобрано":1.0,"Задач внедрено":1.0,"Место по сообществам":42.0,"Место по задачам":13.0,"Задач решено":2.5},{"Задач поставлено":0.0,"Data-debatЫ":0.0,"Фед округ":"ЮФО","Место в рейтинге":17.0,"Data-хакатоны":32.0,"Ретинг по развитию сообщества":5.22,"Рейтинг по внедрению":8.0,"Место по внедрениям":12.0,"Общий рейтинг":13.22,"Рейтинг регионов по задачам":0.0,"Разместил цифровую практику на СМАРТЕКЕ":0.0,"Цифровой наставник":0.0,"Количество команд победителей из региона":1.0,"Субъект РФ":"Республика Адыгея (Адыгея)","Задач отобрано":0.0,"Задач внедрено":2.0,"Место по сообществам":10.0,"Место по задачам":0.0,"Задач решено":0.0},{"Задач поставлено":0.0,"Data-debatЫ":0.0,"Фед округ":"ЮФО","Место в рейтинге":0.0,"Data-хакатоны":3.0,"Ретинг по развитию сообщества":0.0,"Рейтинг по внедрению":0.0,"Место по внедрениям":0.0,"Общий рейтинг":0.0,"Рейтинг регионов по задачам":0.0,"Разместил цифровую практику на СМАРТЕКЕ":0.0,"Цифровой наставник":0.0,"Количество команд победителей из региона":0.0,"Субъект РФ":"Республика Калмыкия","Задач отобрано":0.0,"Задач внедрено":0.0,"Место по сообществам":0.0,"Место по задачам":0.0,"Задач решено":0.0},{"Задач поставлено":1.0,"Data-debatЫ":0.0,"Фед округ":"ЮФО","Место в рейтинге":25.0,"Data-хакатоны":38.0,"Ретинг по развитию сообщества":0.79,"Рейтинг по внедрению":8.0,"Место по внедрениям":12.0,"Общий рейтинг":8.84,"Рейтинг регионов по задачам":0.05,"Разместил цифровую практику на СМАРТЕКЕ":0.0,"Цифровой наставник":0.0,"Количество команд победителей из региона":0.0,"Субъект РФ":"Республика Крым","Задач отобрано":0.0,"Задач внедрено":2.0,"Место по сообществам":38.0,"Место по задачам":31.0,"Задач решено":0.0},{"Задач поставлено":3.0,"Data-debatЫ":1.0,"Фед округ":"ЮФО","Место в рейтинге":4.0,"Data-хакатоны":332.0,"Ретинг по развитию сообщества":27.71,"Рейтинг по внедрению":18.0,"Место по внедрениям":6.0,"Общий рейтинг":50.31,"Рейтинг регионов по задачам":4.6,"Разместил цифровую практику на СМАРТЕКЕ":1.0,"Цифровой наставник":1.0,"Количество команд победителей из региона":2.0,"Субъект РФ":"Ростовская область","Задач отобрано":3.0,"Задач внедрено":3.0,"Место по сообществам":2.0,"Место по задачам":9.0,"Задач решено":3.5},{"Задач поставлено":2.0,"Data-debatЫ":0.0,"Фед округ":"УрФО","Место в рейтинге":56.0,"Data-хакатоны":9.0,"Ретинг по развитию сообщества":0.0,"Рейтинг по внедрению":0.0,"Место по внедрениям":0.0,"Общий рейтинг":1.2,"Рейтинг регионов по задачам":1.2,"Разместил цифровую практику на СМАРТЕКЕ":0.0,"Цифровой наставник":0.0,"Количество команд победителей из региона":0.0,"Субъект РФ":"Курганская область","Задач отобрано":2.0,"Задач внедрено":0.0,"Место по сообществам":0.0,"Место по задачам":20.0,"Задач решено":0.0},{"Задач поставлено":13.0,"Data-debatЫ":1.0,"Фед округ":"УрФО","Место в рейтинге":3.0,"Data-хакатоны":191.0,"Ретинг по развитию сообщества":21.61,"Рейтинг по внедрению":20.0,"Место по внедрениям":4.0,"Общий рейтинг":60.81,"Рейтинг регионов по задачам":19.2,"Разместил цифровую практику на СМАРТЕКЕ":0.0,"Цифровой наставник":0.0,"Количество команд победителей из региона":5.0,"Субъект РФ":"Свердловская область","Задач отобрано":8.0,"Задач внедрено":4.0,"Место по сообществам":3.0,"Место по задачам":1.0,"Задач решено":15.0},{"Задач поставлено":3.0,"Data-debatЫ":0.0,"Фед округ":"УрФО","Место в рейтинге":21.0,"Data-хакатоны":65.0,"Ретинг по развитию сообщества":0.9,"Рейтинг по внедрению":6.0,"Место по внедрениям":13.0,"Общий рейтинг":9.98,"Рейтинг регионов по задачам":3.08,"Разместил цифровую практику на СМАРТЕКЕ":0.0,"Цифровой наставник":0.0,"Количество команд победителей из региона":0.0,"Субъект РФ":"Тюменская область","Задач отобрано":1.0,"Задач внедрено":1.0,"Место по сообществам":29.0,"Место по задачам":11.0,"Задач решено":2.5},{"Задач поставлено":6.0,"Data-debatЫ":0.0,"Фед округ":"УрФО","Место в рейтинге":5.0,"Data-хакатоны":207.0,"Ретинг по развитию сообщества":8.3,"Рейтинг по внедрению":22.0,"Место по внедрениям":2.0,"Общий рейтинг":34.9,"Рейтинг регионов по задачам":4.6,"Разместил цифровую практику на СМАРТЕКЕ":1.0,"Цифровой наставник":1.0,"Количество команд победителей из региона":1.0,"Субъект РФ":"Челябинская область","Задач отобрано":4.0,"Задач внедрено":3.0,"Место по сообществам":5.0,"Место по задачам":9.0,"Задач решено":3.5},{"Задач поставлено":7.0,"Data-debatЫ":0.0,"Фед округ":"УрФО","Место в рейтинге":8.0,"Data-хакатоны":77.0,"Ретинг по развитию сообщества":5.48,"Рейтинг по внедрению":12.0,"Место по внедрениям":9.0,"Общий рейтинг":26.03,"Рейтинг регионов по задачам":8.55,"Разместил цифровую практику на СМАРТЕКЕ":0.0,"Цифровой наставник":0.0,"Количество команд победителей из региона":1.0,"Субъект РФ":"Ханты-Мансийский автономный округ — Югра","Задач отобрано":5.0,"Задач внедрено":2.0,"Место по сообществам":8.0,"Место по задачам":5.0,"Задач решено":5.0},{"Задач поставлено":2.0,"Data-debatЫ":0.0,"Фед округ":"УрФО","Место в рейтинге":62.0,"Data-хакатоны":16.0,"Ретинг по развитию сообщества":0.0,"Рейтинг по внедрению":0.0,"Место по внедрениям":0.0,"Общий рейтинг":0.6,"Рейтинг регионов по задачам":0.6,"Разместил цифровую практику на СМАРТЕКЕ":0.0,"Цифровой наставник":0.0,"Количество команд победителей из региона":0.0,"Субъект РФ":"Ямало-Ненецкий автономный округ","Задач отобрано":2.0,"Задач внедрено":0.0,"Место по сообществам":0.0,"Место по задачам":26.0,"Задач решено":0.0},{"Задач поставлено":0.0,"Data-debatЫ":0.0,"Фед округ":"СФО","Место в рейтинге":0.0,"Data-хакатоны":23.0,"Ретинг по развитию сообщества":0.0,"Рейтинг по внедрению":0.0,"Место по внедрениям":0.0,"Общий рейтинг":0.0,"Рейтинг регионов по задачам":0.0,"Разместил цифровую практику на СМАРТЕКЕ":0.0,"Цифровой наставник":0.0,"Количество команд победителей из региона":0.0,"Субъект РФ":"Алтайский край","Задач отобрано":0.0,"Задач внедрено":0.0,"Место по сообществам":0.0,"Место по задачам":0.0,"Задач решено":0.0},{"Задач поставлено":2.0,"Data-debatЫ":0.0,"Фед округ":"СФО","Место в рейтинге":22.0,"Data-хакатоны":33.0,"Ретинг по развитию сообщества":0.77,"Рейтинг по внедрению":6.0,"Место по внедрениям":13.0,"Общий рейтинг":9.7,"Рейтинг регионов по задачам":2.93,"Разместил цифровую практику на СМАРТЕКЕ":0.0,"Цифровой наставник":0.0,"Количество команд победителей из региона":0.0,"Субъект РФ":"Иркутская область","Задач отобрано":1.0,"Задач внедрено":1.0,"Место по сообществам":41.0,"Место по задачам":12.0,"Задач решено":2.5},{"Задач поставлено":4.0,"Data-debatЫ":0.0,"Фед округ":"СФО","Место в рейтинге":29.0,"Data-хакатоны":38.0,"Ретинг по развитию сообщества":0.78,"Рейтинг по внедрению":6.0,"Место по внедрениям":13.0,"Общий рейтинг":8.13,"Рейтинг регионов по задачам":1.35,"Разместил цифровую практику на СМАРТЕКЕ":0.0,"Цифровой наставник":0.0,"Количество команд победителей из региона":0.0,"Субъект РФ":"Кемеровская область","Задач отобрано":1.0,"Задач внедрено":1.0,"Место по сообществам":39.0,"Место по задачам":18.0,"Задач решено":0.0},{"Задач поставлено":3.0,"Data-debatЫ":0.0,"Фед округ":"СФО","Место в рейтинге":35.0,"Data-хакатоны":45.0,"Ретинг по развитию сообщества":0.0,"Рейтинг по внедрению":6.0,"Место по внедрениям":13.0,"Общий рейтинг":7.2,"Рейтинг регионов по задачам":1.2,"Разместил цифровую практику на СМАРТЕКЕ":0.0,"Цифровой наставник":0.0,"Количество команд победителей из региона":0.0,"Субъект РФ":"Красноярский край","Задач отобрано":1.0,"Задач внедрено":1.0,"Место по сообществам":0.0,"Место по задачам":20.0,"Задач решено":0.0},{"Задач поставлено":4.0,"Data-debatЫ":0.0,"Фед округ":"СФО","Место в рейтинге":52.0,"Data-хакатоны":121.0,"Ретинг по развитию сообщества":1.33,"Рейтинг по внедрению":0.0,"Место по внедрениям":0.0,"Общий рейтинг":2.68,"Рейтинг регионов по задачам":1.35,"Разместил цифровую практику на СМАРТЕКЕ":0.0,"Цифровой наставник":0.0,"Количество команд победителей из региона":0.0,"Субъект РФ":"Новосибирская область","Задач отобрано":1.0,"Задач внедрено":0.0,"Место по сообществам":25.0,"Место по задачам":18.0,"Задач решено":0.0},{"Задач поставлено":1.0,"Data-debatЫ":1.0,"Фед округ":"СФО","Место в рейтинге":46.0,"Data-хакатоны":101.0,"Ретинг по развитию сообщества":3.63,"Рейтинг по внедрению":0.0,"Место по внедрениям":0.0,"Общий рейтинг":3.68,"Рейтинг регионов по задачам":0.05,"Разместил цифровую практику на СМАРТЕКЕ":0.0,"Цифровой наставник":0.0,"Количество команд победителей из региона":0.0,"Субъект РФ":"Омская область","Задач отобрано":0.0,"Задач внедрено":0.0,"Место по сообществам":16.0,"Место по задачам":31.0,"Задач решено":0.0},{"Задач поставлено":2.0,"Data-debatЫ":0.0,"Фед округ":"СФО","Место в рейтинге":58.0,"Data-хакатоны":7.0,"Ретинг по развитию сообщества":0.0,"Рейтинг по внедрению":0.0,"Место по внедрениям":0.0,"Общий рейтинг":1.05,"Рейтинг регионов по задачам":1.05,"Разместил цифровую практику на СМАРТЕКЕ":0.0,"Цифровой наставник":0.0,"Количество команд победителей из региона":0.0,"Субъект РФ":"Республика Алтай","Задач отобрано":1.0,"Задач внедрено":0.0,"Место по сообществам":0.0,"Место по задачам":22.0,"Задач решено":0.0},{"Задач поставлено":2.0,"Data-debatЫ":0.0,"Фед округ":"СФО","Место в рейтинге":64.0,"Data-хакатоны":3.0,"Ретинг по развитию сообщества":0.0,"Рейтинг по внедрению":0.0,"Место по внедрениям":0.0,"Общий рейтинг":0.2,"Рейтинг регионов по задачам":0.2,"Разместил цифровую практику на СМАРТЕКЕ":0.0,"Цифровой наставник":0.0,"Количество команд победителей из региона":0.0,"Субъект РФ":"Республика Тыва","Задач отобрано":0.0,"Задач внедрено":0.0,"Место по сообществам":0.0,"Место по задачам":29.0,"Задач решено":0.0},{"Задач поставлено":0.0,"Data-debatЫ":0.0,"Фед округ":"СФО","Место в рейтинге":0.0,"Data-хакатоны":12.0,"Ретинг по развитию сообщества":0.0,"Рейтинг по внедрению":0.0,"Место по внедрениям":0.0,"Общий рейтинг":0.0,"Рейтинг регионов по задачам":0.0,"Разместил цифровую практику на СМАРТЕКЕ":0.0,"Цифровой наставник":0.0,"Количество команд победителей из региона":0.0,"Субъект РФ":"Республика Хакасия","Задач отобрано":0.0,"Задач внедрено":0.0,"Место по сообществам":0.0,"Место по задачам":0.0,"Задач решено":0.0},{"Задач поставлено":8.0,"Data-debatЫ":1.0,"Фед округ":"СФО","Место в рейтинге":6.0,"Data-хакатоны":76.0,"Ретинг по развитию сообщества":9.18,"Рейтинг по внедрению":17.0,"Место по внедрениям":7.0,"Общий рейтинг":31.71,"Рейтинг регионов по задачам":5.53,"Разместил цифровую практику на СМАРТЕКЕ":2.0,"Цифровой наставник":1.0,"Количество команд победителей из региона":3.0,"Субъект РФ":"Томская область","Задач отобрано":8.0,"Задач внедрено":3.0,"Место по сообществам":4.0,"Место по задачам":7.0,"Задач решено":5.0},{"Задач поставлено":0.0,"Data-debatЫ":0.0,"Фед округ":"СЗФО","Место в рейтинге":0.0,"Data-хакатоны":9.0,"Ретинг по развитию сообщества":0.0,"Рейтинг по внедрению":0.0,"Место по внедрениям":0.0,"Общий рейтинг":0.0,"Рейтинг регионов по задачам":0.0,"Разместил цифровую практику на СМАРТЕКЕ":0.0,"Цифровой наставник":0.0,"Количество команд победителей из региона":0.0,"Субъект РФ":"Архангельская область","Задач отобрано":0.0,"Задач внедрено":0.0,"Место по сообществам":0.0,"Место по задачам":0.0,"Задач решено":0.0},{"Задач поставлено":0.0,"Data-debatЫ":0.0,"Фед округ":"СЗФО","Место в рейтинге":61.0,"Data-хакатоны":45.0,"Ретинг по развитию сообщества":0.83,"Рейтинг по внедрению":0.0,"Место по внедрениям":0.0,"Общий рейтинг":0.83,"Рейтинг регионов по задачам":0.0,"Разместил цифровую практику на СМАРТЕКЕ":0.0,"Цифровой наставник":0.0,"Количество команд победителей из региона":0.0,"Субъект РФ":"Вологодская область","Задач отобрано":0.0,"Задач внедрено":0.0,"Место по сообществам":32.0,"Место по задачам":0.0,"Задач решено":0.0},{"Задач поставлено":9.0,"Data-debatЫ":0.0,"Фед округ":"СЗФО","Место в рейтинге":14.0,"Data-хакатоны":228.0,"Ретинг по развитию сообщества":7.59,"Рейтинг по внедрению":6.0,"Место по внедрениям":13.0,"Общий рейтинг":16.39,"Рейтинг регионов по задачам":2.8,"Разместил цифровую практику на СМАРТЕКЕ":0.0,"Цифровой наставник":0.0,"Количество команд победителей из региона":1.0,"Субъект РФ":"Санкт-Петербург","Задач отобрано":3.0,"Задач внедрено":1.0,"Место по сообществам":7.0,"Место по задачам":14.0,"Задач решено":0.0},{"Задач поставлено":1.0,"Data-debatЫ":1.0,"Фед округ":"СЗФО","Место в рейтинге":42.0,"Data-хакатоны":30.0,"Ретинг по развитию сообщества":2.91,"Рейтинг по внедрению":2.0,"Место по внедрениям":14.0,"Общий рейтинг":5.81,"Рейтинг регионов по задачам":0.9,"Разместил цифровую практику на СМАРТЕКЕ":0.0,"Цифровой наставник":0.0,"Количество команд победителей из региона":0.0,"Субъект РФ":"Калининградская область","Задач отобрано":1.0,"Задач внедрено":1.0,"Место по сообществам":20.0,"Место по задачам":25.0,"Задач решено":0.0},{"Задач поставлено":4.0,"Data-debatЫ":0.0,"Фед округ":"СЗФО","Место в рейтинге":55.0,"Data-хакатоны":4.0,"Ретинг по развитию сообщества":0.0,"Рейтинг по внедрению":0.0,"Место по внедрениям":0.0,"Общий рейтинг":1.25,"Рейтинг регионов по задачам":1.25,"Разместил цифровую практику на СМАРТЕКЕ":0.0,"Цифровой наставник":0.0,"Количество команд победителей из региона":0.0,"Субъект РФ":"Ленинградская область","Задач отобрано":1.0,"Задач внедрено":0.0,"Место по сообществам":0.0,"Место по задачам":19.0,"Задач решено":0.0},{"Задач поставлено":1.0,"Data-debatЫ":0.0,"Фед округ":"СЗФО","Место в рейтинге":65.0,"Data-хакатоны":8.0,"Ретинг по развитию сообщества":0.0,"Рейтинг по внедрению":0.0,"Место по внедрениям":0.0,"Общий рейтинг":0.05,"Рейтинг регионов по задачам":0.05,"Разместил цифровую практику на СМАРТЕКЕ":0.0,"Цифровой наставник":0.0,"Количество команд победителей из региона":0.0,"Субъект РФ":"Мурманская область","Задач отобрано":0.0,"Задач внедрено":0.0,"Место по сообществам":0.0,"Место по задачам":31.0,"Задач решено":0.0},{"Задач поставлено":1.0,"Data-debatЫ":0.0,"Фед округ":"СЗФО","Место в рейтинге":18.0,"Data-хакатоны":0.0,"Ретинг по развитию сообщества":0.0,"Рейтинг по внедрению":10.0,"Место по внедрениям":11.0,"Общий рейтинг":12.78,"Рейтинг регионов по задачам":2.78,"Разместил цифровую практику на СМАРТЕКЕ":0.0,"Цифровой наставник":0.0,"Количество команд победителей из региона":0.0,"Субъект РФ":"Ненецкий автономный округ","Задач отобрано":1.0,"Задач внедрено":1.0,"Место по сообществам":0.0,"Место по задачам":15.0,"Задач решено":2.5},{"Задач поставлено":8.0,"Data-debatЫ":0.0,"Фед округ":"СЗФО","Место в рейтинге":2.0,"Data-хакатоны":50.0,"Ретинг по развитию сообщества":2.78,"Рейтинг по внедрению":45.0,"Место по внедрениям":1.0,"Общий рейтинг":61.26,"Рейтинг регионов по задачам":13.48,"Разместил цифровую практику на СМАРТЕКЕ":2.0,"Цифровой наставник":1.0,"Количество команд победителей из региона":1.0,"Субъект РФ":"Новгородская область","Задач отобрано":4.0,"Задач внедрено":9.0,"Место по сообществам":21.0,"Место по задачам":3.0,"Задач решено":12.5},{"Задач поставлено":0.0,"Data-debatЫ":0.0,"Фед округ":"СЗФО","Место в рейтинге":53.0,"Data-хакатоны":6.0,"Ретинг по развитию сообщества":0.0,"Рейтинг по внедрению":2.0,"Место по внедрениям":14.0,"Общий рейтинг":2.0,"Рейтинг регионов по задачам":0.0,"Разместил цифровую практику на СМАРТЕКЕ":0.0,"Цифровой наставник":0.0,"Количество команд победителей из региона":0.0,"Субъект РФ":"Псковская область","Задач отобрано":0.0,"Задач внедрено":1.0,"Место по сообществам":0.0,"Место по задачам":0.0,"Задач решено":0.0},{"Задач поставлено":2.0,"Data-debatЫ":0.0,"Фед округ":"СЗФО","Место в рейтинге":24.0,"Data-хакатоны":13.0,"Ретинг по развитию сообщества":0.0,"Рейтинг по внедрению":8.0,"Место по внедрениям":12.0,"Общий рейтинг":9.05,"Рейтинг регионов по задачам":1.05,"Разместил цифровую практику на СМАРТЕКЕ":0.0,"Цифровой наставник":0.0,"Количество команд победителей из региона":0.0,"Субъект РФ":"Республика Карелия","Задач отобрано":1.0,"Задач внедрено":2.0,"Место по сообществам":0.0,"Место по задачам":22.0,"Задач решено":0.0},{"Задач поставлено":1.0,"Data-debatЫ":0.0,"Фед округ":"СЗФО","Место в рейтинге":60.0,"Data-хакатоны":21.0,"Ретинг по развитию сообщества":0.0,"Рейтинг по внедрению":0.0,"Место по внедрениям":0.0,"Общий рейтинг":0.9,"Рейтинг регионов по задачам":0.9,"Разместил цифровую практику на СМАРТЕКЕ":0.0,"Цифровой наставник":0.0,"Количество команд победителей из региона":0.0,"Субъект РФ":"Республика Коми","Задач отобрано":1.0,"Задач внедрено":0.0,"Место по сообществам":0.0,"Место по задачам":25.0,"Задач решено":0.0},{"Задач поставлено":2.0,"Data-debatЫ":0.0,"Фед округ":"ДФО","Место в рейтинге":27.0,"Data-хакатоны":106.0,"Ретинг по развитию сообщества":1.41,"Рейтинг по внедрению":6.0,"Место по внедрениям":13.0,"Общий рейтинг":8.46,"Рейтинг регионов по задачам":1.05,"Разместил цифровую практику на СМАРТЕКЕ":0.0,"Цифровой наставник":0.0,"Количество команд победителей из региона":0.0,"Субъект РФ":"Амурская область","Задач отобрано":1.0,"Задач внедрено":1.0,"Место по сообществам":24.0,"Место по задачам":22.0,"Задач решено":0.0},{"Задач поставлено":0.0,"Data-debatЫ":0.0,"Фед округ":"ДФО","Место в рейтинге":0.0,"Data-хакатоны":4.0,"Ретинг по развитию сообщества":0.0,"Рейтинг по внедрению":0.0,"Место по внедрениям":0.0,"Общий рейтинг":0.0,"Рейтинг регионов по задачам":0.0,"Разместил цифровую практику на СМАРТЕКЕ":0.0,"Цифровой наставник":0.0,"Количество команд победителей из региона":0.0,"Субъект РФ":"Еврейская автономная область","Задач отобрано":0.0,"Задач внедрено":0.0,"Место по сообществам":0.0,"Место по задачам":0.0,"Задач решено":0.0},{"Задач поставлено":6.0,"Data-debatЫ":0.0,"Фед округ":"ДФО","Место в рейтинге":28.0,"Data-хакатоны":19.0,"Ретинг по развитию сообщества":0.0,"Рейтинг по внедрению":6.0,"Место по внедрениям":13.0,"Общий рейтинг":8.3,"Рейтинг регионов по задачам":2.3,"Разместил цифровую практику на СМАРТЕКЕ":0.0,"Цифровой наставник":0.0,"Количество команд победителей из региона":0.0,"Субъект РФ":"Забайкальский край","Задач отобрано":2.0,"Задач внедрено":1.0,"Место по сообществам":0.0,"Место по задачам":16.0,"Задач решено":0.0},{"Задач поставлено":0.0,"Data-debatЫ":0.0,"Фед округ":"ДФО","Место в рейтинге":0.0,"Data-хакатоны":4.0,"Ретинг по развитию сообщества":0.0,"Рейтинг по внедрению":0.0,"Место по внедрениям":0.0,"Общий рейтинг":0.0,"Рейтинг регионов по задачам":0.0,"Разместил цифровую практику на СМАРТЕКЕ":0.0,"Цифровой наставник":0.0,"Количество команд победителей из региона":0.0,"Субъект РФ":"Камчатский край","Задач отобрано":0.0,"Задач внедрено":0.0,"Место по сообществам":0.0,"Место по задачам":0.0,"Задач решено":0.0},{"Задач поставлено":0.0,"Data-debatЫ":0.0,"Фед округ":"ДФО","Место в рейтинге":53.0,"Data-хакатоны":2.0,"Ретинг по развитию сообщества":0.0,"Рейтинг по внедрению":2.0,"Место по внедрениям":14.0,"Общий рейтинг":2.0,"Рейтинг регионов по задачам":0.0,"Разместил цифровую практику на СМАРТЕКЕ":0.0,"Цифровой наставник":0.0,"Количество команд победителей из региона":0.0,"Субъект РФ":"Магаданская область","Задач отобрано":0.0,"Задач внедрено":1.0,"Место по сообществам":0.0,"Место по задачам":0.0,"Задач решено":0.0},{"Задач поставлено":7.0,"Data-debatЫ":0.0,"Фед округ":"ДФО","Место в рейтинге":15.0,"Data-хакатоны":69.0,"Ретинг по развитию сообщества":0.86,"Рейтинг по внедрению":8.0,"Место по внедрениям":12.0,"Общий рейтинг":15.69,"Рейтинг регионов по задачам":6.83,"Разместил цифровую практику на СМАРТЕКЕ":0.0,"Цифровой наставник":0.0,"Количество команд победителей из региона":0.0,"Субъект РФ":"Приморский край","Задач отобрано":6.0,"Задач внедрено":2.0,"Место по сообществам":31.0,"Место по задачам":6.0,"Задач решено":2.5},{"Задач поставлено":0.0,"Data-debatЫ":0.0,"Фед округ":"ДФО","Место в рейтинге":50.0,"Data-хакатоны":74.0,"Ретинг по развитию сообщества":1.04,"Рейтинг по внедрению":2.0,"Место по внедрениям":14.0,"Общий рейтинг":3.04,"Рейтинг регионов по задачам":0.0,"Разместил цифровую практику на СМАРТЕКЕ":0.0,"Цифровой наставник":0.0,"Количество команд победителей из региона":0.0,"Субъект РФ":"Республика Бурятия","Задач отобрано":0.0,"Задач внедрено":1.0,"Место по сообществам":28.0,"Место по задачам":0.0,"Задач решено":0.0},{"Задач поставлено":9.0,"Data-debatЫ":1.0,"Фед округ":"ДФО","Место в рейтинге":10.0,"Data-хакатоны":44.0,"Ретинг по развитию сообщества":3.36,"Рейтинг по внедрению":15.0,"Место по внедрениям":8.0,"Общий рейтинг":23.81,"Рейтинг регионов по задачам":5.45,"Разместил цифровую практику на СМАРТЕКЕ":1.0,"Цифровой наставник":0.0,"Количество команд победителей из региона":0.0,"Субъект РФ":"Республика Саха (Якутия)","Задач отобрано":7.0,"Задач внедрено":4.0,"Место по сообществам":18.0,"Место по задачам":8.0,"Задач решено":2.0},{"Задач поставлено":2.0,"Data-debatЫ":0.0,"Фед округ":"ДФО","Место в рейтинге":49.0,"Data-хакатоны":15.0,"Ретинг по развитию сообщества":0.0,"Рейтинг по внедрению":2.0,"Место по внедрениям":14.0,"Общий рейтинг":3.05,"Рейтинг регионов по задачам":1.05,"Разместил цифровую практику на СМАРТЕКЕ":0.0,"Цифровой наставник":0.0,"Количество команд победителей из региона":0.0,"Субъект РФ":"Сахалинская область","Задач отобрано":1.0,"Задач внедрено":1.0,"Место по сообществам":0.0,"Место по задачам":22.0,"Задач решено":0.0},{"Задач поставлено":0.0,"Data-debatЫ":0.0,"Фед округ":"ДФО","Место в рейтинге":26.0,"Data-хакатоны":27.0,"Ретинг по развитию сообщества":0.77,"Рейтинг по внедрению":8.0,"Место по внедрениям":12.0,"Общий рейтинг":8.77,"Рейтинг регионов по задачам":0.0,"Разместил цифровую практику на СМАРТЕКЕ":0.0,"Цифровой наставник":0.0,"Количество команд победителей из региона":0.0,"Субъект РФ":"Хабаровский край","Задач отобрано":0.0,"Задач внедрено":2.0,"Место по сообществам":40.0,"Место по задачам":0.0,"Задач решено":0.0},{"Задач поставлено":0.0,"Data-debatЫ":0.0,"Фед округ":"ДФО","Место в рейтинге":0.0,"Data-хакатоны":0.0,"Ретинг по развитию сообщества":0.0,"Рейтинг по внедрению":0.0,"Место по внедрениям":0.0,"Общий рейтинг":0.0,"Рейтинг регионов по задачам":0.0,"Разместил цифровую практику на СМАРТЕКЕ":0.0,"Цифровой наставник":0.0,"Количество команд победителей из региона":0.0,"Субъект РФ":"Чукотский автономный округ","Задач отобрано":0.0,"Задач внедрено":0.0,"Место по сообществам":0.0,"Место по задачам":0.0,"Задач решено":0.0}]